{
    "decks": [
        {
            "id": "cybersec.deck.patients",
            "resetonexhaustion": true,
            "spec": [
                "patient.lowrisk",
                "patient.highrisk",
                "patient.lowrisk",
                "patient.lowrisk",
                "patient.lowrisk",
                "patient.highrisk"
            ]
        },
        {
            "id": "cybersec.deck.thiefscenarios",
            "resetonexhaustion": true,
            "spec": [
                "cybersec.scenario.email.thief.sickchild",
                "cybersec.scenario.email.thief.drugaddict"
            ]
        },
        {
            "id": "cybersec.deck.dailytasks",
            "resetonexhaustion": true,
            "spec": [
                "dailytask.read.email",
                "dailytask.drink.coffee",
                "scenario.read.email",
                "dailytask.read.logs",
                "dailytask.read.email",
                "cybersec.scenario.thief1",
                "scenario.read.email",
                "scenario.read.email",
                "dailytask.read.email",
                "dailytask.drink.coffe",
                "dailytask.read.logs",
                "scenario.read.email",
                "dailytask.drink.coffe",
                "cybersec.scenario.thief2",
                "dailytask.read.email"
            ]
        }
    ]
}